jenn/__init__.py
jenn/core/__init__.py
jenn/core/activation.py
jenn/core/cache.py
jenn/core/cost.py
jenn/core/data.py
jenn/core/model.py
jenn/core/optimization.py
jenn/core/parameters.py
jenn/core/propagation.py
jenn/core/schema.json
jenn/core/training.py
jenn/post_processing/__init__.py
jenn/post_processing/_actual_by_predicted.py
jenn/post_processing/_contours.py
jenn/post_processing/_convergence.py
jenn/post_processing/_goodness_of_fit.py
jenn/post_processing/_histogram.py
jenn/post_processing/_residual_by_predicted.py
jenn/post_processing/_sensitivities.py
jenn/post_processing/_styling.py
jenn/post_processing/metrics.py
jenn/synthetic_data/__init__.py
jenn/synthetic_data/linear.py
jenn/synthetic_data/parabola.py
jenn/synthetic_data/rastrigin.py
jenn/synthetic_data/rosenbrock.py
jenn/synthetic_data/sinusoid.py
jenn/utilities/__init__.py
jenn/utilities/_finite_difference.py
jenn/utilities/_jmp.py
jenn/utilities/_rbf.py
jenn/utilities/_sample.py
jenn-2.0.0.dist-info/LICENSE
jenn-2.0.0.dist-info/METADATA
jenn-2.0.0.dist-info/WHEEL
jenn-2.0.0.dist-info/top_level.txt
jenn-2.0.0.dist-info/RECORD
