Metadata-Version: 2.1
Name: jenn
Version: 2.0.0
Summary: Jacobian-Enhanced Neural Nets (JENN)
Author-email: "Steven H. Berguin" <stevenberguin@gmail.com>
Project-URL: Documentation, https://shb84.github.io/JENN/
Project-URL: Homepage, https://github.com/shb84/JENN
Project-URL: Issues, https://github.com/shb84/JENN/issues
Classifier: Programming Language :: Python :: 3 :: Only
Classifier: License :: OSI Approved :: MIT License
Classifier: Operating System :: OS Independent
Classifier: Intended Audience :: Developers
Classifier: Intended Audience :: Science/Research
Requires-Python: >=3.9
License-File: LICENSE
Requires-Dist: jsonpointer
Requires-Dist: jsonschema
Requires-Dist: orjson
Requires-Dist: numpy
Requires-Dist: matplotlib
